{
  "schemaVersion": 1,
  "id": "example-addon",
  "version": "${version}",
  "name": "Example Addon",
  "description": "BlackOut Client Addon",
  "authors": [ "Limon_TH "],
  "contact": { "sources": "https://github.com/LimonTH/Blackout-CE" },
  "license": "GPL-3.0",
  "icon": "assets/template/icon.png",
  "environment": "*",
  "entrypoints": {
    "bodevelopment/client/blackout": [
      "com.example.template.ExampleAddon"
    ]
  },
  "mixins": [
    "template.mixins.json"
  ],
  "depends": {
    "fabricloader": ">=${loader_version}",
    "fabric-api": "*",
    "minecraft": "${minecraft_version}"
  }
}
